.long-description.html
README.rst
setup.py
src/collective/__init__.py
src/collective.behavior.salable.egg-info/PKG-INFO
src/collective.behavior.salable.egg-info/SOURCES.txt
src/collective.behavior.salable.egg-info/dependency_links.txt
src/collective.behavior.salable.egg-info/entry_points.txt
src/collective.behavior.salable.egg-info/namespace_packages.txt
src/collective.behavior.salable.egg-info/not-zip-safe
src/collective.behavior.salable.egg-info/requires.txt
src/collective.behavior.salable.egg-info/top_level.txt
src/collective/behavior/__init__.py
src/collective/behavior/salable/__init__.py
src/collective/behavior/salable/behavior.py
src/collective/behavior/salable/configure.zcml
src/collective/behavior/salable/interfaces.py
src/collective/behavior/salable/schema.py
src/collective/behavior/salable/upgrades.py
src/collective/behavior/salable/upgrades.zcml
src/collective/behavior/salable/docs/CONTRIBUTORS.rst
src/collective/behavior/salable/docs/CREDITS.rst
src/collective/behavior/salable/docs/HISTORY.rst
src/collective/behavior/salable/docs/INSTALL.rst
src/collective/behavior/salable/docs/LICENSE.rst
src/collective/behavior/salable/locales/collective.behavior.salable.pot
src/collective/behavior/salable/locales/fi/LC_MESSAGES/collective.behavior.salable.po
src/collective/behavior/salable/profiles/default/catalog.xml
src/collective/behavior/salable/profiles/default/metadata.xml
src/collective/behavior/salable/tests/__init__.py
src/collective/behavior/salable/tests/base.py
src/collective/behavior/salable/tests/test_ISalable.py
src/collective/behavior/salable/tests/test_Salable.py
src/collective/behavior/salable/tests/test_setup.py
src/collective/behavior/salable/tests/test_upgrades.py